claude_plus-2.9.3.dist-info/licenses/LICENSE
config/__init__.py
config/config.yaml
core/__init__.py
core/claude_integration.py
core/config_manager.py
core/config_utils.py
core/control_panel.py
core/control_panel_app.py
core/conversation_viewer.py
core/daemon.py
core/dashboard.py
core/env_manager.py
core/error_handler.py
core/input_router.py
core/japanese_ui.py
core/notifications.py
core/pane_scroll_controller.py
core/pattern_matcher.py
core/process_manager.py
core/screen_controller.py
core/scroll_helper.py
core/sound_player.py
core/stream_dashboard.py
core/tmux_attach_wrapper.sh
core/tmux_sound_helper.sh
core/zero_config.py
engines/__init__.py
engines/auto_yes.py
claude_plus-2.9.3.dist-info/METADATA
claude_plus-2.9.3.dist-info/WHEEL
claude_plus-2.9.3.dist-info/entry_points.txt
claude_plus-2.9.3.dist-info/top_level.txt
claude_plus-2.9.3.dist-info/RECORD
