Metadata-Version: 2.4
Name: claude-plus
Version: 2.9.3
Summary: プロ級の実装を自動化する日本語完全対応の開発プラットフォーム - Claude Code統合により、会話だけで開発が完結
Author-email: Claude++ Development Team <noreply@claude-plus.dev>
Maintainer-email: Claude++ Community <support@claude-plus.dev>
License-Expression: MIT
Project-URL: Homepage, https://github.com/simeji03/Claude-Plus
Project-URL: Repository, https://github.com/simeji03/Claude-Plus
Project-URL: Documentation, https://github.com/simeji03/Claude-Plus/blob/main/docs
Project-URL: Issues, https://github.com/simeji03/Claude-Plus/issues
Keywords: claude,automation,development,japanese,日本語,git,tmux,ai,productivity,cursor
Classifier: Development Status :: 4 - Beta
Classifier: Intended Audience :: Developers
Classifier: Intended Audience :: End Users/Desktop
Classifier: Natural Language :: Japanese
Classifier: Natural Language :: English
Classifier: Programming Language :: Python :: 3
Classifier: Programming Language :: Python :: 3.10
Classifier: Programming Language :: Python :: 3.11
Classifier: Programming Language :: Python :: 3.12
Classifier: Programming Language :: Python :: 3.13
Classifier: Topic :: Software Development
Classifier: Topic :: System :: System Shells
Classifier: Topic :: Text Processing :: Linguistic
Classifier: Environment :: Console
Classifier: Operating System :: MacOS
Classifier: Operating System :: POSIX :: Linux
Requires-Python: >=3.10
License-File: LICENSE
Requires-Dist: PyYAML>=6.0
Requires-Dist: click>=8.0.0
Requires-Dist: colorama>=0.4.6
Requires-Dist: rich>=13.0.0
Requires-Dist: pexpect>=4.8.0
Requires-Dist: watchdog>=3.0.0
Requires-Dist: psutil>=5.9.0
Provides-Extra: dev
Requires-Dist: pytest>=7.0.0; extra == "dev"
Requires-Dist: black>=22.0.0; extra == "dev"
Requires-Dist: flake8>=5.0.0; extra == "dev"
Requires-Dist: mypy>=1.0.0; extra == "dev"
Dynamic: license-file
